interface/__init__.py
interface/interface.py
interface/interface.pyi
interface/labels.py
meta_interface-0.0.1.1.1.dist-info/LICENSE
meta_interface-0.0.1.1.1.dist-info/METADATA
meta_interface-0.0.1.1.1.dist-info/WHEEL
meta_interface-0.0.1.1.1.dist-info/top_level.txt
meta_interface-0.0.1.1.1.dist-info/RECORD
