Metadata-Version: 2.1
Name: meta-interface
Version: 0.0.1.1.1
Summary: A tiny project that introduces the interface concept to Python.
Author-email: Caewinix <Caewinix@yeah.net>
Project-URL: Homepage, https://github.com/Caewinix/meta-interface
Project-URL: Bug Tracker, https://github.com/Caewinix/meta-interface/issues
Classifier: Programming Language :: Python :: 3
Classifier: License :: OSI Approved :: MIT License
Classifier: Operating System :: OS Independent
Requires-Python: >=3.7
License-File: LICENSE
